libashish/__init__.py
libashish/cli.py
libashish/models.py
libashish/proxy_data.py
libashish/real_data.py
libashish/synthetic_data.py
libashish/tuttusa_datasets.py
libashish/utils.py
libashish-0.3.dist-info/LICENSE
libashish-0.3.dist-info/METADATA
libashish-0.3.dist-info/WHEEL
libashish-0.3.dist-info/top_level.txt
libashish-0.3.dist-info/RECORD
