Metadata-Version: 2.1
Name: libashish
Version: 0.3
Summary: first pypi deploy
Home-page: https://github.com/CRLannister/pypitest
Author: Ashish
Author-email: agarwal.ashish.singhal@gmail.com
License: MIT
Download-URL: https://github.com/CRLannister/pypitest/archive/v_01.tar.gz
Keywords: first,pypi,package
Platform: UNKNOWN
Classifier: Development Status :: 3 - Alpha
Classifier: Intended Audience :: Developers
Classifier: Topic :: Software Development :: Build Tools
Classifier: License :: OSI Approved :: MIT License
Classifier: Programming Language :: Python :: 3
Classifier: Programming Language :: Python :: 3.4
Classifier: Programming Language :: Python :: 3.5
Classifier: Programming Language :: Python :: 3.6
License-File: LICENSE
Requires-Dist: pydantic
Requires-Dist: numpy
Requires-Dist: pandas
Requires-Dist: tensorflow
Requires-Dist: unidecode
Requires-Dist: transliterate
Requires-Dist: sklearn
Requires-Dist: scipy
Requires-Dist: matplotlib
Requires-Dist: dload
Requires-Dist: requests
Requires-Dist: google
Requires-Dist: tqdm
